mythx_cli/__init__.py
mythx_cli/cli.py
mythx_cli/util.py
mythx_cli/analysis/__init__.py
mythx_cli/analysis/list.py
mythx_cli/analysis/report.py
mythx_cli/analysis/status.py
mythx_cli/analyze/__init__.py
mythx_cli/analyze/command.py
mythx_cli/analyze/scribble.py
mythx_cli/analyze/solidity.py
mythx_cli/analyze/truffle.py
mythx_cli/analyze/util.py
mythx_cli/formatter/__init__.py
mythx_cli/formatter/base.py
mythx_cli/formatter/json.py
mythx_cli/formatter/simple_stdout.py
mythx_cli/formatter/tabular.py
mythx_cli/formatter/util.py
mythx_cli/group/__init__.py
mythx_cli/group/close.py
mythx_cli/group/list.py
mythx_cli/group/open.py
mythx_cli/group/status.py
mythx_cli/render/__init__.py
mythx_cli/render/command.py
mythx_cli/render/util.py
mythx_cli/render/templates/aesthetic.html
mythx_cli/render/templates/default.html
mythx_cli/render/templates/default.md
mythx_cli/render/templates/layout.html
mythx_cli/render/templates/layout.md
mythx_cli/version/__init__.py
mythx_cli/version/command.py
mythx_cli-0.7.3.dist-info/AUTHORS.rst
mythx_cli-0.7.3.dist-info/LICENSE
mythx_cli-0.7.3.dist-info/METADATA
mythx_cli-0.7.3.dist-info/WHEEL
mythx_cli-0.7.3.dist-info/entry_points.txt
mythx_cli-0.7.3.dist-info/top_level.txt
mythx_cli-0.7.3.dist-info/RECORD
