Metadata-Version: 2.1
Name: mythx-cli
Version: 0.7.3
Summary: A command line interface for the MythX smart contract security analysis API
Home-page: https://github.com/dmuhs/mythx-cli
Author: Dominik Muhs
Author-email: dominik.muhs@consensys.net
License: MIT license
Keywords: mythx-cli
Classifier: Development Status :: 4 - Beta
Classifier: License :: OSI Approved :: MIT License
Classifier: Natural Language :: English
Classifier: Intended Audience :: Developers
Classifier: Intended Audience :: Education
Classifier: Intended Audience :: Information Technology
Classifier: Topic :: Security
Classifier: Topic :: Software Development :: Libraries :: Python Modules
Classifier: Topic :: Software Development :: Quality Assurance
Classifier: Topic :: Terminals :: Terminal Emulators/X Terminals
Classifier: Topic :: Utilities
Classifier: Typing :: Typed
Classifier: Programming Language :: Python :: 3
Classifier: Programming Language :: Python :: 3.6
Classifier: Programming Language :: Python :: 3.7
Classifier: Programming Language :: Python :: 3.7
Classifier: Programming Language :: Python :: 3.8
Classifier: Programming Language :: Python :: Implementation :: PyPy
License-File: LICENSE
License-File: AUTHORS.rst
Requires-Dist: Click (==8.1.3)
Requires-Dist: py-solc-x (==1.1.1)
Requires-Dist: pythx (==1.7.3)
Requires-Dist: tabulate (==0.8.9)
Requires-Dist: Jinja2 (==3.1.1)
Requires-Dist: htmlmin (==0.1.12)
Requires-Dist: PyYAML (==6.0)
Requires-Dist: MarkupSafe (==2.0.1)
